muradmymodule/__init__.py
muradmymodule/add.py
muradmymodule/subtract.py
muradmymodule/extras/__init__.py
muradmymodule/extras/divide.py
muradmymodule/extras/multiply.py
muradmymodule-0.0.4.dist-info/METADATA
muradmymodule-0.0.4.dist-info/WHEEL
muradmymodule-0.0.4.dist-info/top_level.txt
muradmymodule-0.0.4.dist-info/RECORD
